therapi/__init__.py
therapi/authentication.py
therapi/exceptions.py
therapi/thingipy.py
therapi-0.0.4.dist-info/WHEEL
therapi-0.0.4.dist-info/LICENSE
therapi-0.0.4.dist-info/METADATA
therapi-0.0.4.dist-info/RECORD
