Metadata-Version: 2.1
Name: therapi
Version: 0.0.4
Summary: Therapy to ease the pain of writing boilerplate JSON API consumers.
License: MIT
Author: Helmut Irle
Author-email: me@helmut.dev
Requires-Python: >=3.8,<4.0
Classifier: License :: OSI Approved :: MIT License
Classifier: Programming Language :: Python :: 3
Classifier: Programming Language :: Python :: 3.8
Classifier: Programming Language :: Python :: 3.9
Classifier: Programming Language :: Python :: 3.10
Classifier: Programming Language :: Python :: 3.11
Requires-Dist: requests (>=2.28.2,<3.0.0)
